rex_score/__init__.py
rex_score/resample_exposure.py
rex_score/utils/preprocessing.py
rex_score-1.1.dist-info/METADATA
rex_score-1.1.dist-info/WHEEL
rex_score-1.1.dist-info/licenses/LICENSE
rex_score-1.1.dist-info/RECORD
