Metadata-Version: 2.4
Name: rex_score
Version: 1.1
Summary: Library for experiments on measuring resample exposure similarity in heterogeneous datasets..
Project-URL: Homepage, https://github.com/notna07/resample-exposure-similairty
Project-URL: Bug Tracker, https://github.com/notna07/resample-exposure-similairty/issues
Author: Anton D. Lautrup, Hafiz Saud Arshad, Tobias Hyrup, Muhammad Rajabinasab
License-File: LICENSE
Classifier: License :: OSI Approved :: MIT License
Classifier: Operating System :: OS Independent
Classifier: Programming Language :: Python :: 3
Requires-Python: >=3.7
Requires-Dist: click>=8.1.3
Requires-Dist: joblib~=1.4.2
Requires-Dist: numpy~=1.26
Requires-Dist: pandas>=2.0
